<?xml version="1.0" encoding="utf-8"?>
<HattrickData>
    <FileName>players.xml</FileName>
    <Version>2.7</Version>
    <UserID>13900623</UserID>
    <FetchedDate>2025-05-28 12:21:51</FetchedDate>
    <UserSupporterTier>platinum</UserSupporterTier>
    <IsYouth>False</IsYouth>
    <ActionType>viewoldcoaches</ActionType>
    <IsPlayingMatch>False</IsPlayingMatch>
    <Team>
        <TeamID>834283</TeamID>
        <TeamName>Social Uruguayo</TeamName>
        <PlayerList>
            <Player>
                <PlayerID>428738415</PlayerID>
                <FirstName>Cédric</FirstName>
                <NickName></NickName>
                <LastName>Jaffre</LastName>
                <PlayerNumber>100</PlayerNumber>
                <Age>42</Age>
                <AgeDays>109</AgeDays>
                <ArrivalDate>0001-01-01 00:00:00</ArrivalDate>
                <OwnerNotes></OwnerNotes>
                <TSI>730</TSI>
                <PlayerForm>2</PlayerForm>
                <Statement></Statement>
                <Experience>10</Experience>
                <Loyalty>20</Loyalty>
                <MotherClubBonus>False</MotherClubBonus>
                <Leadership>5</Leadership>
                <Salary>0</Salary>
                <IsAbroad>0</IsAbroad>
                <Agreeability>3</Agreeability>
                <Aggressiveness>0</Aggressiveness>
                <Honesty>2</Honesty>
                <LeagueGoals>0</LeagueGoals>
                <CupGoals>0</CupGoals>
                <FriendliesGoals>0</FriendliesGoals>
                <CareerGoals>0</CareerGoals>
                <CareerHattricks>0</CareerHattricks>
                <MatchesCurrentTeam>0</MatchesCurrentTeam>
                <GoalsCurrentTeam>0</GoalsCurrentTeam>
                <AssistsCurrentTeam>0</AssistsCurrentTeam>
                <CareerAssists>0</CareerAssists>
                <Specialty>0</Specialty>
                <TransferListed>False</TransferListed>
                <NationalTeamID>0</NationalTeamID>
                <CountryID>7</CountryID>
                <Caps>0</Caps>
                <CapsU20>0</CapsU20>
                <Cards>0</Cards>
                <InjuryLevel>-1</InjuryLevel>
                <TrainerData>
                    <TrainerType>2</TrainerType>
                    <TrainerSkillLevel>5</TrainerSkillLevel>
                </TrainerData>
            </Player>
            <Player>
                <PlayerID>422766532</PlayerID>
                <FirstName>Diego</FirstName>
                <NickName></NickName>
                <LastName>Baruzzo</LastName>
                <PlayerNumber>100</PlayerNumber>
                <Age>47</Age>
                <AgeDays>15</AgeDays>
                <ArrivalDate>0001-01-01 00:00:00</ArrivalDate>
                <OwnerNotes></OwnerNotes>
                <TSI>0</TSI>
                <PlayerForm>4</PlayerForm>
                <Statement></Statement>
                <Experience>7</Experience>
                <Loyalty>20</Loyalty>
                <MotherClubBonus>False</MotherClubBonus>
                <Leadership>5</Leadership>
                <Salary>0</Salary>
                <IsAbroad>1</IsAbroad>
                <Agreeability>4</Agreeability>
                <Aggressiveness>2</Aggressiveness>
                <Honesty>1</Honesty>
                <LeagueGoals>0</LeagueGoals>
                <CupGoals>0</CupGoals>
                <FriendliesGoals>0</FriendliesGoals>
                <CareerGoals>0</CareerGoals>
                <CareerHattricks>0</CareerHattricks>
                <MatchesCurrentTeam>0</MatchesCurrentTeam>
                <GoalsCurrentTeam>0</GoalsCurrentTeam>
                <AssistsCurrentTeam>0</AssistsCurrentTeam>
                <CareerAssists>0</CareerAssists>
                <Specialty>4</Specialty>
                <TransferListed>False</TransferListed>
                <NationalTeamID>0</NationalTeamID>
                <CountryID>7</CountryID>
                <Caps>0</Caps>
                <CapsU20>0</CapsU20>
                <Cards>0</Cards>
                <InjuryLevel>-1</InjuryLevel>
                <TrainerData>
                    <TrainerType>0</TrainerType>
                    <TrainerSkillLevel>4</TrainerSkillLevel>
                </TrainerData>
            </Player>
        </PlayerList>
    </Team>
</HattrickData>